message_send_platform_invitation/__init__.py
message_send_platform_invitation/country_constants.py
message_send_platform_invitation/messagesendplatform.py
message_send_platform_invitation-0.0.3.dist-info/METADATA
message_send_platform_invitation-0.0.3.dist-info/WHEEL
message_send_platform_invitation-0.0.3.dist-info/top_level.txt
message_send_platform_invitation-0.0.3.dist-info/RECORD
