Metadata-Version: 2.1
Name: message-send-platform-invitation
Version: 0.0.3
Summary: PyPI Package for Circles message_send_platform_invitation Python
Home-page: https://github.com/circles-zone/message-send-platform-invitation-local-python-package
Author: Circles
Author-email: info@circlez.ai
Classifier: Programming Language :: Python :: 3
Classifier: License :: Other/Proprietary License
Classifier: Operating System :: OS Independent
Requires-Dist: pytest >=7.4.0
Requires-Dist: user-context-remote >=0.0.17
Requires-Dist: python-sdk-local >=0.0.27
Requires-Dist: messages-local
